kameris-1.2.3.data/purelib/kameris/__init__.py
kameris-1.2.3.data/purelib/kameris/__main__.py
kameris-1.2.3.data/purelib/kameris/job_steps/__init__.py
kameris-1.2.3.data/purelib/kameris/job_steps/_classifiers.py
kameris-1.2.3.data/purelib/kameris/job_steps/_command.py
kameris-1.2.3.data/purelib/kameris/job_steps/backend.py
kameris-1.2.3.data/purelib/kameris/job_steps/classify.py
kameris-1.2.3.data/purelib/kameris/job_steps/mds.py
kameris-1.2.3.data/purelib/kameris/job_steps/selection.py
kameris-1.2.3.data/purelib/kameris/schemas/file_urls.json
kameris-1.2.3.data/purelib/kameris/schemas/job_options.json
kameris-1.2.3.data/purelib/kameris/schemas/settings.json
kameris-1.2.3.data/purelib/kameris/scripts/generation_cgr_windows_avx2.exe
kameris-1.2.3.data/purelib/kameris/scripts/generation_cgr_windows_sse41.exe
kameris-1.2.3.data/purelib/kameris/scripts/generation_dists_windows_avx2.exe
kameris-1.2.3.data/purelib/kameris/scripts/generation_dists_windows_sse41.exe
kameris-1.2.3.data/purelib/kameris/scripts/make_plots.wls
kameris-1.2.3.data/purelib/kameris/subcommands/__init__.py
kameris-1.2.3.data/purelib/kameris/subcommands/classify.py
kameris-1.2.3.data/purelib/kameris/subcommands/run_job.py
kameris-1.2.3.data/purelib/kameris/subcommands/summarize.py
kameris-1.2.3.data/purelib/kameris/utils/__init__.py
kameris-1.2.3.data/purelib/kameris/utils/defaults.py
kameris-1.2.3.data/purelib/kameris/utils/download_utils.py
kameris-1.2.3.data/purelib/kameris/utils/file_formats.py
kameris-1.2.3.data/purelib/kameris/utils/fs_utils.py
kameris-1.2.3.data/purelib/kameris/utils/job_utils.py
kameris-1.2.3.data/purelib/kameris/utils/launcher_utils.py
kameris-1.2.3.data/purelib/kameris/utils/platform_utils.py
kameris-1.2.3.data/purelib/tests/__init__.py
kameris-1.2.3.data/purelib/tests/conftest.py
kameris-1.2.3.data/purelib/tests/helpers.py
kameris-1.2.3.data/purelib/tests/test_demo.py
kameris-1.2.3.dist-info/METADATA
kameris-1.2.3.dist-info/RECORD
kameris-1.2.3.dist-info/WHEEL
kameris-1.2.3.dist-info/entry_points.txt
kameris-1.2.3.dist-info/top_level.txt
