Metadata-Version: 2.1
Name: kameris
Version: 1.2.3
Summary: A fast, user-friendly analysis and evaluation pipeline for some DNA sequence classification tasks.
Home-page: https://github.com/stephensolis/kameris/
Author: Stephen
Author-email: stephsolis@gmail.com
License: MIT
Platform: UNKNOWN
Classifier: Development Status :: 4 - Beta
Classifier: License :: OSI Approved :: MIT License
Classifier: Programming Language :: Python :: 2
Classifier: Programming Language :: Python :: 2.7
Classifier: Programming Language :: Python :: 3
Classifier: Programming Language :: Python :: 3.4
Classifier: Programming Language :: Python :: 3.5
Classifier: Programming Language :: Python :: 3.6
Classifier: Programming Language :: Python :: 3.7
Classifier: Topic :: Scientific/Engineering :: Artificial Intelligence
Classifier: Topic :: Scientific/Engineering :: Bio-Informatics
Requires-Dist: appdirs
Requires-Dist: backports.tempfile
Requires-Dist: jsonschema
Requires-Dist: kameris-formats
Requires-Dist: numpy
Requires-Dist: requests (>=2.18.0)
Requires-Dist: ruamel.yaml
Requires-Dist: psutil
Requires-Dist: scikit-learn (==0.19.1)
Requires-Dist: scipy
Requires-Dist: six
Requires-Dist: stopit
Requires-Dist: tabulate
Requires-Dist: tqdm
Requires-Dist: watchtower
Requires-Dist: x86cpu
